gravopt.py
gravopt-0.1.0.dist-info/licenses/LICENSE
gravopt-0.1.0.dist-info/METADATA
gravopt-0.1.0.dist-info/WHEEL
gravopt-0.1.0.dist-info/top_level.txt
gravopt-0.1.0.dist-info/RECORD
