Metadata-Version: 2.4
Name: gravopt
Version: 0.1.0
Summary: A short description of what your package does.
Author-email: Dimitar Kretske <kretski1@gmail.com>
License: MIT
Classifier: Programming Language :: Python :: 3
Classifier: License :: OSI Approved :: MIT License
Classifier: Operating System :: OS Independent
Requires-Python: >=3.8
License-File: LICENSE
Dynamic: license-file
